compbaseball/__init__.py
compbaseball/baseball.py
compbaseball/build_data.py
compbaseball/inputs.json
compbaseball/playerchoices.json
compbaseball-0.1.14.dist-info/LICENSE
compbaseball-0.1.14.dist-info/METADATA
compbaseball-0.1.14.dist-info/WHEEL
compbaseball-0.1.14.dist-info/top_level.txt
compbaseball-0.1.14.dist-info/RECORD
